Workbook

Sheet Cover Page
A1: Medicare DRG Profatibility & Sensitivity Analysis Good Samiritan Hospital FY2023
B6: Content
B8: Output & Summary
B9: Input
B10: Master Table
B11: SC1: Admission Drop Scenario
B12: SC2: LOS Reduce Scenario
B13: Good Samaritan Hospital Data
B14: Ohio Urban Hospitals Financial

Sheet Output & Summary
B2: Output Summary & Visualization
C6: Total Net Margin | D6: Net Margin %∆ From Baseline
B7: FY2023 Baseline | C7: ='Master Table'!N68 -> 9494691.4 | D7: 0
B8: Admission Drop | C8: ='Master Table'!P68 -> 8744232 | D8: =(C8-C7)/C7 -> -0.079039892
B9: LOS Reduction | C9: ='Master Table'!X68 -> 10813389 | D9: =(C9-C7)/C7 -> 0.13888793

Sheet Input
B2: Inputs/Assumptions | C2: Value
B3: Average WI | C3: ='Ohio Urban Hospitals Financial '!P47 -> 0.937236
B4: Does WI>1? | C4: =C3>1 -> FALSE
B6: Operating Standards Amounts By CMS
B7: Labor Related WI>1 | C7: 4310
B8: Non-Labor Related WI>1 | C8: 2065
B10: Labor Related WI<=1 | C10: 3952.96
B11: Non-Labor Related WI<=1 | C11: 2422.78
B13: Capital Standard Federal Rate | C13: 483.76
B15: Operating Base Rate (Labor*WI + Non-labor) | C15: =IF(C4,C7*C3+C8,C10*C3+C11) -> 6127.6364
B17: Average CCR | C17: ='Ohio Urban Hospitals Financial '!K47 -> 0.267243
B19: Total Admission Cost | C19: 3603
B20: Fixed Cost/admit | C20: 2161.8
B21: Variable Cost/day | C21: 1441.2

Sheet Master Table
A1: Baseline Data | O1: Admission Drop Scenario 8% | S1: LOS Reduction Scenario
A2: MS-DRG | B2: MDC | C2: MDC Group | D2: TYPE | E2: MS-DRG Title | F2: Weights | G2: Geometric mean LOS | H2: Operating Payment/ Discharge | I2: Capital Payment/ Discharge | J2: Base Payment/ Discharge | K2: Cost/ Discharge | L2: Net Margin/Dis | M2: Discharge Volume | N2: Total net Margin | O2: New Volume | P2: New Total Net Margin | Q2: New Net Gain (Loss) In Margin | R2: % Change in Total Margin | S2: New LOS | T2: New Cost/Discharge | U2: Cost Saving $/DRG Volume | V2: %∆ In Cost/Dis | W2: New Net Margin/Dis | X2: New Total net Margin2
A3: 023 | B3: 01 | C3: MDC 01 Nervous System | D3: SURG | E3: CRANIOTOMY WITH MAJOR DEVICE IMPLANT OR ACUTE COMPLEX CNS PRINCIPAL DIAGNOSIS WITH MCC OR CHEMOTHERAPY IMPLANT OR EPILEPSY WITH NEUROSTIMULATOR | F3: 5.7314 | G3: 7.3 | H3: =F3*Input!$C$15 -> 35119.935 | I3: =F3*Input!$C$13 -> 2772.6221 | J3: =H3+I3 -> 37892.557 | K3: =(Input!$C$21*'Master Table'!G3)+Input!$C$20 -> 12682.56 | L3: =J3-K3 -> 25209.997 | M3: =VLOOKUP(A3,'Good Samaritan Hospital'!$G:$I,3,FALSE) -> 14 | N3: =L3*M3 -> 352939.96 | O3: ='SC1 Admission Drop Scenario'!S3 -> 13 | P3: ='SC1 Admission Drop Scenario'!T3 -> 327729.97 | Q3: =Table1[[#This Row],[New Total Net Margin]]-Table1[[#This Row],[Total net Margin]] -> -25209.997 | R3: =(Table1[[#This Row],[New Total Net Margin]]-Table1[[#This Row],[Total net Margin]])/Table1[[#This Row],[Total net Margin]] -> -0.071428571 | S3: ='SC2 Reduce LOS'!P3 -> 6.8 | T3: ='SC2 Reduce LOS'!Q3 -> 11961.96 | U3: =(Table1[[#This Row],[Cost/ Discharge]]-Table1[[#This Row],[New Cost/Discharge]])*Table1[[#This Row],[Discharge Volume]] -> 10088.4 | V3: ='SC2 Reduce LOS'!S3 -> -0.056818182 | W3: ='SC2 Reduce LOS'!T3 -> 25930.597 | X3: ='SC2 Reduce LOS'!U3 -> 363028.36
A4: 025 | B4: 01 | C4: MDC 01 Nervous System | D4: SURG | E4: CRANIOTOMY AND ENDOVASCULAR INTRACRANIAL PROCEDURES WITH MCC | F4: 4.5405 | G4: 6.6 | H4: =F4*Input!$C$15 -> 27822.533 | I4: =F4*Input!$C$13 -> 2196.5123 | J4: =H4+I4 -> 30019.045 | K4: =(Input!$C$21*'Master Table'!G4)+Input!$C$20 -> 11673.72 | L4: =J4-K4 -> 18345.325 | M4: =VLOOKUP(A4,'Good Samaritan Hospital'!$G:$I,3,FALSE) -> 23 | N4: =L4*M4 -> 421942.49 | O4: ='SC1 Admission Drop Scenario'!S4 -> 21 | P4: ='SC1 Admission Drop Scenario'!T4 -> 385251.83 | Q4: =Table1[[#This Row],[New Total Net Margin]]-Table1[[#This Row],[Total net Margin]] -> -36690.651 | R4: =(Table1[[#This Row],[New Total Net Margin]]-Table1[[#This Row],[Total net Margin]])/Table1[[#This Row],[Total net Margin]] -> -0.086956522 | S4: ='SC2 Reduce LOS'!P4 -> 6.1 | T4: ='SC2 Reduce LOS'!Q4 -> 10953.12 | U4: =(Table1[[#This Row],[Cost/ Discharge]]-Table1[[#This Row],[New Cost/Discharge]])*Table1[[#This Row],[Discharge Volume]] -> 16573.8 | V4: ='SC2 Reduce LOS'!S4 -> -0.061728395 | W4: ='SC2 Reduce LOS'!T4 -> 19065.925 | X4: ='SC2 Reduce LOS'!U4 -> 438516.29
A5: 027 | B5: 01 | C5: MDC 01 Nervous System | D5: SURG | E5: CRANIOTOMY AND ENDOVASCULAR INTRACRANIAL PROCEDURES WITHOUT CC/MCC | F5: 2.4954 | G5: 1.8 | H5: =F5*Input!$C$15 -> 15290.904 | I5: =F5*Input!$C$13 -> 1207.1747 | J5: =H5+I5 -> 16498.079 | K5: =(Input!$C$21*'Master Table'!G5)+Input!$C$20 -> 4755.96 | L5: =J5-K5 -> 11742.119 | M5: =VLOOKUP(A5,'Good Samaritan Hospital'!$G:$I,3,FALSE) -> 15 | N5: =L5*M5 -> 176131.78 | O5: ='SC1 Admission Drop Scenario'!S5 -> 14 | P5: ='SC1 Admission Drop Scenario'!T5 -> 164389.66 | Q5: =Table1[[#This Row],[New Total Net Margin]]-Table1[[#This Row],[Total net Margin]] -> -11742.119 | R5: =(Table1[[#This Row],[New Total Net Margin]]-Table1[[#This Row],[Total net Margin]])/Table1[[#This Row],[Total net Margin]] -> -0.066666667 | S5: ='SC2 Reduce LOS'!P5 -> 1.3 | T5: ='SC2 Reduce LOS'!Q5 -> 4035.36 | U5: =(Table1[[#This Row],[Cost/ Discharge]]-Table1[[#This Row],[New Cost/Discharge]])*Table1[[#This Row],[Discharge Volume]] -> 10809 | V5: ='SC2 Reduce LOS'!S5 -> -0.15151515 | W5: ='SC2 Reduce LOS'!T5 -> 12462.719 | X5: ='SC2 Reduce LOS'!U5 -> 186940.78
A6: 057 | B6: 01 | C6: MDC 01 Nervous System | D6: MED | E6: DEGENERATIVE NERVOUS SYSTEM DISORDERS WITHOUT MCC | F6: 1.3015 | G6: 3.8 | H6: =F6*Input!$C$15 -> 7975.1188 | I6: =F6*Input!$C$13 -> 629.61364 | J6: =H6+I6 -> 8604.7324 | K6: =(Input!$C$21*'Master Table'!G6)+Input!$C$20 -> 7638.36 | L6: =J6-K6 -> 966.37244 | M6: =VLOOKUP(A6,'Good Samaritan Hospital'!$G:$I,3,FALSE) -> 14 | N6: =L6*M6 -> 13529.214 | O6: ='SC1 Admission Drop Scenario'!S6 -> 13 | P6: ='SC1 Admission Drop Scenario'!T6 -> 12562.842 | Q6: =Table1[[#This Row],[New Total Net Margin]]-Table1[[#This Row],[Total net Margin]] -> -966.37244 | R6: =(Table1[[#This Row],[New Total Net Margin]]-Table1[[#This Row],[Total net Margin]])/Table1[[#This Row],[Total net Margin]] -> -0.071428571 | S6: ='SC2 Reduce LOS'!P6 -> 3.3 | T6: ='SC2 Reduce LOS'!Q6 -> 6917.76 | U6: =(Table1[[#This Row],[Cost/ Discharge]]-Table1[[#This Row],[New Cost/Discharge]])*Table1[[#This Row],[Discharge Volume]] -> 10088.4 | V6: ='SC2 Reduce LOS'!S6 -> -0.094339623 | W6: ='SC2 Reduce LOS'!T6 -> 1686.9724 | X6: ='SC2 Reduce LOS'!U6 -> 23617.614
A7: 064 | B7: 01 | C7: MDC 01 Nervous System | D7: MED | E7: INTRACRANIAL HEMORRHAGE OR CEREBRAL INFARCTION WITH MCC | F7: 1.972 | G7: 4.5 | H7: =F7*Input!$C$15 -> 12083.699 | I7: =F7*Input!$C$13 -> 953.97472 | J7: =H7+I7 -> 13037.674 | K7: =(Input!$C$21*'Master Table'!G7)+Input!$C$20 -> 8647.2 | L7: =J7-K7 -> 4390.4737 | M7: =VLOOKUP(A7,'Good Samaritan Hospital'!$G:$I,3,FALSE) -> 67 | N7: =L7*M7 -> 294161.74 | O7: ='SC1 Admission Drop Scenario'!S7 -> 62 | P7: ='SC1 Admission Drop Scenario'!T7 -> 272209.37 | Q7: =Table1[[#This Row],[New Total Net Margin]]-Table1[[#This Row],[Total net Margin]] -> -21952.369 | R7: =(Table1[[#This Row],[New Total Net Margin]]-Table1[[#This Row],[Total net Margin]])/Table1[[#This Row],[Total net Margin]] -> -0.074626866 | S7: ='SC2 Reduce LOS'!P7 -> 4 | T7: ='SC2 Reduce LOS'!Q7 -> 7926.6 | U7: =(Table1[[#This Row],[Cost/ Discharge]]-Table1[[#This Row],[New Cost/Discharge]])*Table1[[#This Row],[Discharge Volume]] -> 48280.2 | V7: ='SC2 Reduce LOS'!S7 -> -0.083333333 | W7: ='SC2 Reduce LOS'!T7 -> 5111.0737 | X7: ='SC2 Reduce LOS'!U7 -> 342441.94
A8: 065 | B8: 01 | C8: MDC 01 Nervous System | D8: MED | E8: INTRACRANIAL HEMORRHAGE OR CEREBRAL INFARCTION WITH CC OR TPA IN 24 HOURS | F8: 1.0164 | G8: 2.9 | H8: =F8*Input!$C$15 -> 6228.1297 | I8: =F8*Input!$C$13 -> 491.69366 | J8: =H8+I8 -> 6719.8233 | K8: =(Input!$C$21*'Master Table'!G8)+Input!$C$20 -> 6341.28 | L8: =J8-K8 -> 378.54332 | M8: =VLOOKUP(A8,'Good Samaritan Hospital'!$G:$I,3,FALSE) -> 52 | N8: =L8*M8 -> 19684.253 | O8: ='SC1 Admission Drop Scenario'!S8 -> 48 | P8: ='SC1 Admission Drop Scenario'!T8 -> 18170.079 | Q8: =Table1[[#This Row],[New Total Net Margin]]-Table1[[#This Row],[Total net Margin]] -> -1514.1733 | R8: =(Table1[[#This Row],[New Total Net Margin]]-Table1[[#This Row],[Total net Margin]])/Table1[[#This Row],[Total net Margin]] -> -0.076923077 | S8: ='SC2 Reduce LOS'!P8 -> 2.4 | T8: ='SC2 Reduce LOS'!Q8 -> 5620.68 | U8: =(Table1[[#This Row],[Cost/ Discharge]]-Table1[[#This Row],[New Cost/Discharge]])*Table1[[#This Row],[Discharge Volume]] -> 37471.2 | V8: ='SC2 Reduce LOS'!S8 -> -0.11363636 | W8: ='SC2 Reduce LOS'!T8 -> 1099.1433 | X8: ='SC2 Reduce LOS'!U8 -> 57155.453
A9: 069 | B9: 01 | C9: MDC 01 Nervous System | D9: MED | E9: TRANSIENT ISCHEMIA WITHOUT THROMBOLYTIC | F9: 0.7979 | G9: 2 | H9: =F9*Input!$C$15 -> 4889.2411 | I9: =F9*Input!$C$13 -> 385.9921 | J9: =H9+I9 -> 5275.2332 | K9: =(Input!$C$21*'Master Table'!G9)+Input!$C$20 -> 5044.2 | L9: =J9-K9 -> 231.0332 | M9: =VLOOKUP(A9,'Good Samaritan Hospital'!$G:$I,3,FALSE) -> 11 | N9: =L9*M9 -> 2541.3652 | O9: ='SC1 Admission Drop Scenario'!S9 -> 10 | P9: ='SC1 Admission Drop Scenario'!T9 -> 2310.332 | Q9: =Table1[[#This Row],[New Total Net Margin]]-Table1[[#This Row],[Total net Margin]] -> -231.0332 | R9: =(Table1[[#This Row],[New Total Net Margin]]-Table1[[#This Row],[Total net Margin]])/Table1[[#This Row],[Total net Margin]] -> -0.090909091 | S9: ='SC2 Reduce LOS'!P9 -> 1.5 | T9: ='SC2 Reduce LOS'!Q9 -> 4323.6 | U9: =(Table1[[#This Row],[Cost/ Discharge]]-Table1[[#This Row],[New Cost/Discharge]])*Table1[[#This Row],[Discharge Volume]] -> 7926.6 | V9: ='SC2 Reduce LOS'!S9 -> -0.14285714 | W9: ='SC2 Reduce LOS'!T9 -> 951.6332 | X9: ='SC2 Reduce LOS'!U9 -> 10467.965
A10: 070 | B10: 01 | C10: MDC 01 Nervous System | D10: MED | E10: NONSPECIFIC CEREBROVASCULAR DISORDERS WITH MCC | F10: 1.7242 | G10: 4.6 | H10: =F10*Input!$C$15 -> 10565.271 | I10: =F10*Input!$C$13 -> 834.09899 | J10: =H10+I10 -> 11399.37 | K10: =(Input!$C$21*'Master Table'!G10)+Input!$C$20 -> 8791.32 | L10: =J10-K10 -> 2608.0497 | M10: =VLOOKUP(A10,'Good Samaritan Hospital'!$G:$I,3,FALSE) -> 18 | N10: =L10*M10 -> 46944.895 | O10: ='SC1 Admission Drop Scenario'!S10 -> 17 | P10: ='SC1 Admission Drop Scenario'!T10 -> 44336.845 | Q10: =Table1[[#This Row],[New Total Net Margin]]-Table1[[#This Row],[Total net Margin]] -> -2608.0497 | R10: =(Table1[[#This Row],[New Total Net Margin]]-Table1[[#This Row],[Total net Margin]])/Table1[[#This Row],[Total net Margin]] -> -0.055555556 | S10: ='SC2 Reduce LOS'!P10 -> 4.1 | T10: ='SC2 Reduce LOS'!Q10 -> 8070.72 | U10: =(Table1[[#This Row],[Cost/ Discharge]]-Table1[[#This Row],[New Cost/Discharge]])*Table1[[#This Row],[Discharge Volume]] -> 12970.8 | V10: ='SC2 Reduce LOS'!S10 -> -0.081967213 | W10: ='SC2 Reduce LOS'!T10 -> 3328.6497 | X10: ='SC2 Reduce LOS'!U10 -> 59915.695
A11: 071 | B11: 01 | C11: MDC 01 Nervous System | D11: MED | E11: NONSPECIFIC CEREBROVASCULAR DISORDERS WITH CC | F11: 1.069 | G11: 3.4 | H11: =F11*Input!$C$15 -> 6550.4433 | I11: =F11*Input!$C$13 -> 517.13944 | J11: =H11+I11 -> 7067.5828 | K11: =(Input!$C$21*'Master Table'!G11)+Input!$C$20 -> 7061.88 | L11: =J11-K11 -> 5.7027714 | M11: =VLOOKUP(A11,'Good Samaritan Hospital'!$G:$I,3,FALSE) -> 20 | N11: =L11*M11 -> 114.05543 | O11: ='SC1 Admission Drop Scenario'!S11 -> 18 | P11: ='SC1 Admission Drop Scenario'!T11 -> 102.64989 | Q11: =Table1[[#This Row],[New Total Net Margin]]-Table1[[#This Row],[Total net Margin]] -> -11.405543 | R11: =(Table1[[#This Row],[New Total Net Margin]]-Table1[[#This Row],[Total net Margin]])/Table1[[#This Row],[Total net Margin]] -> -0.1 | S11: ='SC2 Reduce LOS'!P11 -> 2.9 | T11: ='SC2 Reduce LOS'!Q11 -> 6341.28 | U11: =(Table1[[#This Row],[Cost/ Discharge]]-Table1[[#This Row],[New Cost/Discharge]])*Table1[[#This Row],[Discharge Volume]] -> 14412 | V11: ='SC2 Reduce LOS'!S11 -> -0.10204082 | W11: ='SC2 Reduce LOS'!T11 -> 726.30277 | X11: ='SC2 Reduce LOS'!U11 -> 14526.055
A12: 100 | B12: 01 | C12: MDC 01 Nervous System | D12: MED | E12: SEIZURES WITH MCC | F12: 1.921 | G12: 4.4 | H12: =F12*Input!$C$15 -> 11771.19 | I12: =F12*Input!$C$13 -> 929.30296 | J12: =H12+I12 -> 12700.493 | K12: =(Input!$C$21*'Master Table'!G12)+Input!$C$20 -> 8503.08 | L12: =J12-K12 -> 4197.4125 | M12: =VLOOKUP(A12,'Good Samaritan Hospital'!$G:$I,3,FALSE) -> 19 | N12: =L12*M12 -> 79750.838 | O12: ='SC1 Admission Drop Scenario'!S12 -> 17 | P12: ='SC1 Admission Drop Scenario'!T12 -> 71356.013 | Q12: =Table1[[#This Row],[New Total Net Margin]]-Table1[[#This Row],[Total net Margin]] -> -8394.825 | R12: =(Table1[[#This Row],[New Total Net Margin]]-Table1[[#This Row],[Total net Margin]])/Table1[[#This Row],[Total net Margin]] -> -0.10526316 | S12: ='SC2 Reduce LOS'!P12 -> 3.9 | T12: ='SC2 Reduce LOS'!Q12 -> 7782.48 | U12: =(Table1[[#This Row],[Cost/ Discharge]]-Table1[[#This Row],[New Cost/Discharge]])*Table1[[#This Row],[Discharge Volume]] -> 13691.4 | V12: ='SC2 Reduce LOS'!S12 -> -0.084745763 | W12: ='SC2 Reduce LOS'!T12 -> 4918.0125 | X12: ='SC2 Reduce LOS'!U12 -> 93442.238
A13: 101 | B13: 01 | C13: MDC 01 Nervous System | D13: MED | E13: SEIZURES WITHOUT MCC | F13: 0.9015 | G13: 2.6 | H13: =F13*Input!$C$15 -> 5524.0642 | I13: =F13*Input!$C$13 -> 436.10964 | J13: =H13+I13 -> 5960.1739 | K13: =(Input!$C$21*'Master Table'!G13)+Input!$C$20 -> 5908.92 | L13: =J13-K13 -> 51.253871 | M13: =VLOOKUP(A13,'Good Samaritan Hospital'!$G:$I,3,FALSE) -> 14 | N13: =L13*M13 -> 717.5542 | O13: ='SC1 Admission Drop Scenario'!S13 -> 13 | P13: ='SC1 Admission Drop Scenario'!T13 -> 666.30033 | Q13: =Table1[[#This Row],[New Total Net Margin]]-Table1[[#This Row],[Total net Margin]] -> -51.253871 | R13: =(Table1[[#This Row],[New Total Net Margin]]-Table1[[#This Row],[Total net Margin]])/Table1[[#This Row],[Total net Margin]] -> -0.071428571 | S13: ='SC2 Reduce LOS'!P13 -> 2.1 | T13: ='SC2 Reduce LOS'!Q13 -> 5188.32 | U13: =(Table1[[#This Row],[Cost/ Discharge]]-Table1[[#This Row],[New Cost/Discharge]])*Table1[[#This Row],[Discharge Volume]] -> 10088.4 | V13: ='SC2 Reduce LOS'!S13 -> -0.12195122 | W13: ='SC2 Reduce LOS'!T13 -> 771.85387 | X13: ='SC2 Reduce LOS'!U13 -> 10805.954
A14: 175 | B14: 04 | C14: MDC 04 Respiratory System | D14: MED | E14: PULMONARY EMBOLISM WITH MCC OR ACUTE COR PULMONALE | F14: 1.3968 | G14: 3.9 | H14: =F14*Input!$C$15 -> 8559.0825 | I14: =F14*Input!$C$13 -> 675.71597 | J14: =H14+I14 -> 9234.7985 | K14: =(Input!$C$21*'Master Table'!G14)+Input!$C$20 -> 7782.48 | L14: =J14-K14 -> 1452.3185 | M14: =VLOOKUP(A14,'Good Samaritan Hospital'!$G:$I,3,FALSE) -> 16 | N14: =L14*M14 -> 23237.096 | O14: ='SC1 Admission Drop Scenario'!S14 -> 15 | P14: ='SC1 Admission Drop Scenario'!T14 -> 21784.778 | Q14: =Table1[[#This Row],[New Total Net Margin]]-Table1[[#This Row],[Total net Margin]] -> -1452.3185 | R14: =(Table1[[#This Row],[New Total Net Margin]]-Table1[[#This Row],[Total net Margin]])/Table1[[#This Row],[Total net Margin]] -> -0.0625 | S14: ='SC2 Reduce LOS'!P14 -> 3.4 | T14: ='SC2 Reduce LOS'!Q14 -> 7061.88 | U14: =(Table1[[#This Row],[Cost/ Discharge]]-Table1[[#This Row],[New Cost/Discharge]])*Table1[[#This Row],[Discharge Volume]] -> 11529.6 | V14: ='SC2 Reduce LOS'!S14 -> -0.092592593 | W14: ='SC2 Reduce LOS'!T14 -> 2172.9185 | X14: ='SC2 Reduce LOS'!U14 -> 34766.696
... A67: 981 | B67: 00 | C67: MDC 00 Procedures & Diagnoses Not Elsewhere Classified | D67: SURG | E67: EXTENSIVE O.R. PROCEDURES UNRELATED TO PRINCIPAL DIAGNOSIS WITH MCC | F67: 4.5804 | G67: 8.5 | H67: =F67*Input!$C$15 -> 28067.026 | I67: =F67*Input!$C$13 -> 2215.8143 | J67: =H67+I67 -> 30282.84 | K67: =(Input!$C$21*'Master Table'!G67)+Input!$C$20 -> 14412 | L67: =J67-K67 -> 15870.84 | M67: =VLOOKUP(A67,'Good Samaritan Hospital'!$G:$I,3,FALSE) -> 11 | N67: =L67*M67 -> 174579.24 | O67: ='SC1 Admission Drop Scenario'!S67 -> 10 | P67: ='SC1 Admission Drop Scenario'!T67 -> 158708.4 | Q67: =Table1[[#This Row],[New Total Net Margin]]-Table1[[#This Row],[Total net Margin]] -> -15870.84 | R67: =(Table1[[#This Row],[New Total Net Margin]]-Table1[[#This Row],[Total net Margin]])/Table1[[#This Row],[Total net Margin]] -> -0.090909091 | S67: ='SC2 Reduce LOS'!P67 -> 8 | T67: ='SC2 Reduce LOS'!Q67 -> 13691.4 | U67: =(Table1[[#This Row],[Cost/ Discharge]]-Table1[[#This Row],[New Cost/Discharge]])*Table1[[#This Row],[Discharge Volume]] -> 7926.6 | V67: ='SC2 Reduce LOS'!S67 -> -0.05 | W67: ='SC2 Reduce LOS'!T67 -> 16591.44 | X67: ='SC2 Reduce LOS'!U67 -> 182505.84
M68: =SUBTOTAL(109,M3:M67) -> 1830 | N68: =SUBTOTAL(109,N3:N67) -> 9494691.4 | P68: =SUBTOTAL(109,P3:P67) -> 8744232 | R68: =(Table1[[#This Row],[New Total Net Margin]]-Table1[[#This Row],[Total net Margin]])/Table1[[#This Row],[Total net Margin]] -> -0.079039892 | U68: =SUBTOTAL(109,U3:U67) -> 1318698 | X68: =SUBTOTAL(109,X3:X67) -> 10813389

Sheet SC1 Admission Drop Scenario
A1: Baseline Data | S1: Volume Shock Scenario
A2: MS-DRG | B2: MS-DRG | C2: FY 2023 Final Post-Acute DRG | D2: FY 2023 Final Special Pay DRG | E2: MDC | F2: TYPE | G2: MS-DRG Title | H2: Weights | I2: Geometric mean LOS | J2: Operating payment per discharge | K2: Capital payment per discharge | L2: Total base payment per discharge | M2: Total base payment per discharge | N2: Total base payment per discharge | O2: Total Cost per Admission | P2: Net Margin/Dis | Q2: Discharge Volume | R2: Total net Margin | S2: New Volume | T2: New Total Net Margin | U2: % Change in Total Margin
A3: =TRIM(B3) -> 023 | B3: 023 | C3: Yes | D3: Yes | E3: 01 | F3: SURG | G3: CRANIOTOMY WITH MAJOR DEVICE IMPLANT OR ACUTE COMPLEX CNS PRINCIPAL DIAGNOSIS WITH MCC OR CHEMOTHERAPY IMPLANT OR EPILEPSY WITH NEUROSTIMULATOR | H3: 5.7314 | I3: 7.3 | J3: =H3*Input!$C$15 -> 35119.935 | K3: =H3*Input!$C$13 -> 2772.6221 | L3: =J3+K3 -> 37892.557 | M3: =L3*Input!$C$17 -> 10126.521 | N3: =L3-M3 -> 27766.037 | O3: =(Input!$C$21*'Master Table'!G3)+Input!$C$20 -> 12682.56 | P3: =L3-O3 -> 25209.997 | Q3: =VLOOKUP(A3,'Good Samaritan Hospital'!$G:$I,3,FALSE) -> 14 | R3: =P3*Q3 -> 352939.96 | S3: =ROUND(Q3*(1-0.08),0) -> 13 | T3: =P3*S3 -> 327729.97 | U3: =(T3-R3)/R3 -> -0.071428571
A4: =TRIM(B4) -> 025 | B4: 025 | C4: Yes | D4: No | E4: 01 | F4: SURG | G4: CRANIOTOMY AND ENDOVASCULAR INTRACRANIAL PROCEDURES WITH MCC | H4: 4.5405 | I4: 6.6 | J4: =H4*Input!$C$15 -> 27822.533 | K4: =H4*Input!$C$13 -> 2196.5123 | L4: =J4+K4 -> 30019.045 | M4: =L4*Input!$C$17 -> 8022.3798 | N4: =L4-M4 -> 21996.666 | O4: =(Input!$C$21*'Master Table'!G4)+Input!$C$20 -> 11673.72 | P4: =L4-O4 -> 18345.325 | Q4: =VLOOKUP(A4,'Good Samaritan Hospital'!$G:$I,3,FALSE) -> 23 | R4: =P4*Q4 -> 421942.49 | S4: =ROUND(Q4*(1-0.08),0) -> 21 | T4: =P4*S4 -> 385251.83 | U4: =(T4-R4)/R4 -> -0.086956522
A5: =TRIM(B5) -> 027 | B5: 027 | C5: Yes | D5: No | E5: 01 | F5: SURG | G5: CRANIOTOMY AND ENDOVASCULAR INTRACRANIAL PROCEDURES WITHOUT CC/MCC | H5: 2.4954 | I5: 1.8 | J5: =H5*Input!$C$15 -> 15290.904 | K5: =H5*Input!$C$13 -> 1207.1747 | L5: =J5+K5 -> 16498.079 | M5: =L5*Input!$C$17 -> 4408.996 | N5: =L5-M5 -> 12089.083 | O5: =(Input!$C$21*'Master Table'!G5)+Input!$C$20 -> 4755.96 | P5: =L5-O5 -> 11742.119 | Q5: =VLOOKUP(A5,'Good Samaritan Hospital'!$G:$I,3,FALSE) -> 15 | R5: =P5*Q5 -> 176131.78 | S5: =ROUND(Q5*(1-0.08),0) -> 14 | T5: =P5*S5 -> 164389.66 | U5: =(T5-R5)/R5 -> -0.066666667
A6: =TRIM(B6) -> 057 | B6: 057 | C6: Yes | D6: No | E6: 01 | F6: MED | G6: DEGENERATIVE NERVOUS SYSTEM DISORDERS WITHOUT MCC | H6: 1.3015 | I6: 3.8 | J6: =H6*Input!$C$15 -> 7975.1188 | K6: =H6*Input!$C$13 -> 629.61364 | L6: =J6+K6 -> 8604.7324 | M6: =L6*Input!$C$17 -> 2299.5545 | N6: =L6-M6 -> 6305.1779 | O6: =(Input!$C$21*'Master Table'!G6)+Input!$C$20 -> 7638.36 | P6: =L6-O6 -> 966.37244 | Q6: =VLOOKUP(A6,'Good Samaritan Hospital'!$G:$I,3,FALSE) -> 14 | R6: =P6*Q6 -> 13529.214 | S6: =ROUND(Q6*(1-0.08),0) -> 13 | T6: =P6*S6 -> 12562.842 | U6: =(T6-R6)/R6 -> -0.071428571
A7: =TRIM(B7) -> 064 | B7: 064 | C7: Yes | D7: No | E7: 01 | F7: MED | G7: INTRACRANIAL HEMORRHAGE OR CEREBRAL INFARCTION WITH MCC | H7: 1.972 | I7: 4.5 | J7: =H7*Input!$C$15 -> 12083.699 | K7: =H7*Input!$C$13 -> 953.97472 | L7: =J7+K7 -> 13037.674 | M7: =L7*Input!$C$17 -> 3484.227 | N7: =L7-M7 -> 9553.4467 | O7: =(Input!$C$21*'Master Table'!G7)+Input!$C$20 -> 8647.2 | P7: =L7-O7 -> 4390.4737 | Q7: =VLOOKUP(A7,'Good Samaritan Hospital'!$G:$I,3,FALSE) -> 67 | R7: =P7*Q7 -> 294161.74 | S7: =ROUND(Q7*(1-0.08),0) -> 62 | T7: =P7*S7 -> 272209.37 | U7: =(T7-R7)/R7 -> -0.074626866
A8: =TRIM(B8) -> 065 | B8: 065 | C8: Yes | D8: No | E8: 01 | F8: MED | G8: INTRACRANIAL HEMORRHAGE OR CEREBRAL INFARCTION WITH CC OR TPA IN 24 HOURS | H8: 1.0164 | I8: 2.9 | J8: =H8*Input!$C$15 -> 6228.1297 | K8: =H8*Input!$C$13 -> 491.69366 | L8: =J8+K8 -> 6719.8233 | M8: =L8*Input!$C$17 -> 1795.8257 | N8: =L8-M8 -> 4923.9976 | O8: =(Input!$C$21*'Master Table'!G8)+Input!$C$20 -> 6341.28 | P8: =L8-O8 -> 378.54332 | Q8: =VLOOKUP(A8,'Good Samaritan Hospital'!$G:$I,3,FALSE) -> 52 | R8: =P8*Q8 -> 19684.253 | S8: =ROUND(Q8*(1-0.08),0) -> 48 | T8: =P8*S8 -> 18170.079 | U8: =(T8-R8)/R8 -> -0.076923077
A9: =TRIM(B9) -> 069 | B9: 069 | C9: No | D9: No | E9: 01 | F9: MED | G9: TRANSIENT ISCHEMIA WITHOUT THROMBOLYTIC | H9: 0.7979 | I9: 2 | J9: =H9*Input!$C$15 -> 4889.2411 | K9: =H9*Input!$C$13 -> 385.9921 | L9: =J9+K9 -> 5275.2332 | M9: =L9*Input!$C$17 -> 1409.7691 | N9: =L9-M9 -> 3865.4641 | O9: =(Input!$C$21*'Master Table'!G9)+Input!$C$20 -> 5044.2 | P9: =L9-O9 -> 231.0332 | Q9: =VLOOKUP(A9,'Good Samaritan Hospital'!$G:$I,3,FALSE) -> 11 | R9: =P9*Q9 -> 2541.3652 | S9: =ROUND(Q9*(1-0.08),0) -> 10 | T9: =P9*S9 -> 2310.332 | U9: =(T9-R9)/R9 -> -0.090909091
A10: =TRIM(B10) -> 070 | B10: 070 | C10: Yes | D10: No | E10: 01 | F10: MED | G10: NONSPECIFIC CEREBROVASCULAR DISORDERS WITH MCC | H10: 1.7242 | I10: 4.6 | J10: =H10*Input!$C$15 -> 10565.271 | K10: =H10*Input!$C$13 -> 834.09899 | L10: =J10+K10 -> 11399.37 | M10: =L10*Input!$C$17 -> 3046.4018 | N10: =L10-M10 -> 8352.9679 | O10: =(Input!$C$21*'Master Table'!G10)+Input!$C$20 -> 8791.32 | P10: =L10-O10 -> 2608.0497 | Q10: =VLOOKUP(A10,'Good Samaritan Hospital'!$G:$I,3,FALSE) -> 18 | R10: =P10*Q10 -> 46944.895 | S10: =ROUND(Q10*(1-0.08),0) -> 17 | T10: =P10*S10 -> 44336.845 | U10: =(T10-R10)/R10 -> -0.055555556
A11: =TRIM(B11) -> 071 | B11: 071 | C11: Yes | D11: No | E11: 01 | F11: MED | G11: NONSPECIFIC CEREBROVASCULAR DISORDERS WITH CC | H11: 1.069 | I11: 3.4 | J11: =H11*Input!$C$15 -> 6550.4433 | K11: =H11*Input!$C$13 -> 517.13944 | L11: =J11+K11 -> 7067.5828 | M11: =L11*Input!$C$17 -> 1888.762 | N11: =L11-M11 -> 5178.8207 | O11: =(Input!$C$21*'Master Table'!G11)+Input!$C$20 -> 7061.88 | P11: =L11-O11 -> 5.7027714 | Q11: =VLOOKUP(A11,'Good Samaritan Hospital'!$G:$I,3,FALSE) -> 20 | R11: =P11*Q11 -> 114.05543 | S11: =ROUND(Q11*(1-0.08),0) -> 18 | T11: =P11*S11 -> 102.64989 | U11: =(T11-R11)/R11 -> -0.1
A12: =TRIM(B12) -> 100 | B12: 100 | C12: Yes | D12: No | E12: 01 | F12: MED | G12: SEIZURES WITH MCC | H12: 1.921 | I12: 4.4 | J12: =H12*Input!$C$15 -> 11771.19 | K12: =H12*Input!$C$13 -> 929.30296 | L12: =J12+K12 -> 12700.493 | M12: =L12*Input!$C$17 -> 3394.1177 | N12: =L12-M12 -> 9306.3748 | O12: =(Input!$C$21*'Master Table'!G12)+Input!$C$20 -> 8503.08 | P12: =L12-O12 -> 4197.4125 | Q12: =VLOOKUP(A12,'Good Samaritan Hospital'!$G:$I,3,FALSE) -> 19 | R12: =P12*Q12 -> 79750.838 | S12: =ROUND(Q12*(1-0.08),0) -> 17 | T12: =P12*S12 -> 71356.013 | U12: =(T12-R12)/R12 -> -0.10526316
A13: =TRIM(B13) -> 101 | B13: 101 | C13: Yes | D13: No | E13: 01 | F13: MED | G13: SEIZURES WITHOUT MCC | H13: 0.9015 | I13: 2.6 | J13: =H13*Input!$C$15 -> 5524.0642 | K13: =H13*Input!$C$13 -> 436.10964 | L13: =J13+K13 -> 5960.1739 | M13: =L13*Input!$C$17 -> 1592.8147 | N13: =L13-M13 -> 4367.3591 | O13: =(Input!$C$21*'Master Table'!G13)+Input!$C$20 -> 5908.92 | P13: =L13-O13 -> 51.253871 | Q13: =VLOOKUP(A13,'Good Samaritan Hospital'!$G:$I,3,FALSE) -> 14 | R13: =P13*Q13 -> 717.5542 | S13: =ROUND(Q13*(1-0.08),0) -> 13 | T13: =P13*S13 -> 666.30033 | U13: =(T13-R13)/R13 -> -0.071428571
A14: =TRIM(B14) -> 175 | B14: 175 | C14: Yes | D14: No | E14: 04 | F14: MED | G14: PULMONARY EMBOLISM WITH MCC OR ACUTE COR PULMONALE | H14: 1.3968 | I14: 3.9 | J14: =H14*Input!$C$15 -> 8559.0825 | K14: =H14*Input!$C$13 -> 675.71597 | L14: =J14+K14 -> 9234.7985 | M14: =L14*Input!$C$17 -> 2467.9353 | N14: =L14-M14 -> 6766.8633 | O14: =(Input!$C$21*'Master Table'!G14)+Input!$C$20 -> 7782.48 | P14: =L14-O14 -> 1452.3185 | Q14: =VLOOKUP(A14,'Good Samaritan Hospital'!$G:$I,3,FALSE) -> 16 | R14: =P14*Q14 -> 23237.096 | S14: =ROUND(Q14*(1-0.08),0) -> 15 | T14: =P14*S14 -> 21784.778 | U14: =(T14-R14)/R14 -> -0.0625
... A66: =TRIM(B66) -> 948 | B66: 948 | C66: Yes | D66: No | E66: 23 | F66: MED | G66: SIGNS AND SYMPTOMS WITHOUT MCC | H66: 0.7776 | I66: 2.5 | J66: =H66*Input!$C$15 -> 4764.8501 | K66: =H66*Input!$C$13 -> 376.17178 | L66: =J66+K66 -> 5141.0219 | M66: =L66*Input!$C$17 -> 1373.9021 | N66: =L66-M66 -> 3767.1198 | O66: =(Input!$C$21*'Master Table'!G66)+Input!$C$20 -> 5764.8 | P66: =L66-O66 -> -623.77814 | Q66: =VLOOKUP(A66,'Good Samaritan Hospital'!$G:$I,3,FALSE) -> 18 | R66: =P66*Q66 -> -11228.007 | S66: =ROUND(Q66*(1-0.08),0) -> 17 | T66: =P66*S66 -> -10604.228 | U66: =(T66-R66)/R66 -> -0.055555556
A67: =TRIM(B67) -> 981 | B67: 981 | C67: Yes | D67: No | F67: SURG | G67: EXTENSIVE O.R. PROCEDURES UNRELATED TO PRINCIPAL DIAGNOSIS WITH MCC | H67: 4.5804 | I67: 8.5 | J67: =H67*Input!$C$15 -> 28067.026 | K67: =H67*Input!$C$13 -> 2215.8143 | L67: =J67+K67 -> 30282.84 | M67: =L67*Input!$C$17 -> 8092.8771 | N67: =L67-M67 -> 22189.963 | O67: =(Input!$C$21*'Master Table'!G67)+Input!$C$20 -> 14412 | P67: =L67-O67 -> 15870.84 | Q67: =VLOOKUP(A67,'Good Samaritan Hospital'!$G:$I,3,FALSE) -> 11 | R67: =P67*Q67 -> 174579.24 | S67: =ROUND(Q67*(1-0.08),0) -> 10 | T67: =P67*S67 -> 158708.4 | U67: =(T67-R67)/R67 -> -0.090909091
Q68: =SUM(Q3:Q67) -> 1830 | R68: =SUM(R3:R67) -> 9494691.4 | S68: =SUM(S3:S67) -> 1686 | T68: =SUM(T3:T67) -> 8744232 | U68: =(T68-R68)/R68 -> -0.079039892

Sheet SC2 Reduce LOS
A1: Baseline Data | P1: LOS Reduction Scenario
A2: MS-DRG | B2: MDC | C2: TYPE | D2: MS-DRG Title | E2: Weights | F2: Geometric mean LOS | G2: Operating payment per discharge | H2: Capital payment per discharge | I2: Total base payment per discharge | J2: Total base payment per discharge | K2: Total base payment per discharge | L2: Total Cost per Admission | M2: Net Margin/Dis | N2: Discharge Volume | O2: Total net Margin | P2: New LOS | Q2: New Total Cost/Discharge | R2: Cost Saving $/DRG Volume | S2: % In Cost/Dis | T2: New Net Margin/Dis | U2: New Total net Margin
A3: 023 | B3: 01 | C3: SURG | D3: CRANIOTOMY WITH MAJOR DEVICE IMPLANT OR ACUTE COMPLEX CNS PRINCIPAL DIAGNOSIS WITH MCC OR CHEMOTHERAPY IMPLANT OR EPILEPSY WITH NEUROSTIMULATOR | E3: 5.7314 | F3: 7.3 | G3: =E3*Input!$C$15 -> 35119.935 | H3: =E3*Input!$C$13 -> 2772.6221 | I3: =G3+H3 -> 37892.557 | J3: =I3*Input!$C$17 -> 10126.521 | K3: =I3-J3 -> 27766.037 | L3: =(Input!$C$21*'Master Table'!G3)+Input!$C$20 -> 12682.56 | M3: =I3-L3 -> 25209.997 | N3: =VLOOKUP(A3,'Good Samaritan Hospital'!$G:$I,3,FALSE) -> 14 | O3: =M3*N3 -> 352939.96 | P3: =F3-0.5 -> 6.8 | Q3: =(P3*Input!$C$21)+Input!$C$20 -> 11961.96 | R3: =-(Q3-L3)*N3 -> 10088.4 | S3: =(Q3-L3)/L3 -> -0.056818182 | T3: =I3-Q3 -> 25930.597 | U3: =T3*N3 -> 363028.36
A4: 025 | B4: 01 | C4: SURG | D4: CRANIOTOMY AND ENDOVASCULAR INTRACRANIAL PROCEDURES WITH MCC | E4: 4.5405 | F4: 6.6 | G4: =E4*Input!$C$15 -> 27822.533 | H4: =E4*Input!$C$13 -> 2196.5123 | I4: =G4+H4 -> 30019.045 | J4: =I4*Input!$C$17 -> 8022.3798 | K4: =I4-J4 -> 21996.666 | L4: =(Input!$C$21*'Master Table'!G4)+Input!$C$20 -> 11673.72 | M4: =I4-L4 -> 18345.325 | N4: =VLOOKUP(A4,'Good Samaritan Hospital'!$G:$I,3,FALSE) -> 23 | O4: =M4*N4 -> 421942.49 | P4: =F4-0.5 -> 6.1 | Q4: =(P4*Input!$C$21)+Input!$C$20 -> 10953.12 | R4: =-(Q4-L4)*N4 -> 16573.8 | S4: =(Q4-L4)/L4 -> -0.061728395 | T4: =I4-Q4 -> 19065.925 | U4: =T4*N4 -> 438516.29
A5: 027 | B5: 01 | C5: SURG | D5: CRANIOTOMY AND ENDOVASCULAR INTRACRANIAL PROCEDURES WITHOUT CC/MCC | E5: 2.4954 | F5: 1.8 | G5: =E5*Input!$C$15 -> 15290.904 | H5: =E5*Input!$C$13 -> 1207.1747 | I5: =G5+H5 -> 16498.079 | J5: =I5*Input!$C$17 -> 4408.996 | K5: =I5-J5 -> 12089.083 | L5: =(Input!$C$21*'Master Table'!G5)+Input!$C$20 -> 4755.96 | M5: =I5-L5 -> 11742.119 | N5: =VLOOKUP(A5,'Good Samaritan Hospital'!$G:$I,3,FALSE) -> 15 | O5: =M5*N5 -> 176131.78 | P5: =F5-0.5 -> 1.3 | Q5: =(P5*Input!$C$21)+Input!$C$20 -> 4035.36 | R5: =-(Q5-L5)*N5 -> 10809 | S5: =(Q5-L5)/L5 -> -0.15151515 | T5: =I5-Q5 -> 12462.719 | U5: =T5*N5 -> 186940.78
A6: 057 | B6: 01 | C6: MED | D6: DEGENERATIVE NERVOUS SYSTEM DISORDERS WITHOUT MCC | E6: 1.3015 | F6: 3.8 | G6: =E6*Input!$C$15 -> 7975.1188 | H6: =E6*Input!$C$13 -> 629.61364 | I6: =G6+H6 -> 8604.7324 | J6: =I6*Input!$C$17 -> 2299.5545 | K6: =I6-J6 -> 6305.1779 | L6: =(Input!$C$21*'Master Table'!G6)+Input!$C$20 -> 7638.36 | M6: =I6-L6 -> 966.37244 | N6: =VLOOKUP(A6,'Good Samaritan Hospital'!$G:$I,3,FALSE) -> 14 | O6: =M6*N6 -> 13529.214 | P6: =F6-0.5 -> 3.3 | Q6: =(P6*Input!$C$21)+Input!$C$20 -> 6917.76 | R6: =-(Q6-L6)*N6 -> 10088.4 | S6: =(Q6-L6)/L6 -> -0.094339623 | T6: =I6-Q6 -> 1686.9724 | U6: =T6*N6 -> 23617.614
A7: 064 | B7: 01 | C7: MED | D7: INTRACRANIAL HEMORRHAGE OR CEREBRAL INFARCTION WITH MCC | E7: 1.972 | F7: 4.5 | G7: =E7*Input!$C$15 -> 12083.699 | H7: =E7*Input!$C$13 -> 953.97472 | I7: =G7+H7 -> 13037.674 | J7: =I7*Input!$C$17 -> 3484.227 | K7: =I7-J7 -> 9553.4467 | L7: =(Input!$C$21*'Master Table'!G7)+Input!$C$20 -> 8647.2 | M7: =I7-L7 -> 4390.4737 | N7: =VLOOKUP(A7,'Good Samaritan Hospital'!$G:$I,3,FALSE) -> 67 | O7: =M7*N7 -> 294161.74 | P7: =F7-0.5 -> 4 | Q7: =(P7*Input!$C$21)+Input!$C$20 -> 7926.6 | R7: =-(Q7-L7)*N7 -> 48280.2 | S7: =(Q7-L7)/L7 -> -0.083333333 | T7: =I7-Q7 -> 5111.0737 | U7: =T7*N7 -> 342441.94
A8: 065 | B8: 01 | C8: MED | D8: INTRACRANIAL HEMORRHAGE OR CEREBRAL INFARCTION WITH CC OR TPA IN 24 HOURS | E8: 1.0164 | F8: 2.9 | G8: =E8*Input!$C$15 -> 6228.1297 | H8: =E8*Input!$C$13 -> 491.69366 | I8: =G8+H8 -> 6719.8233 | J8: =I8*Input!$C$17 -> 1795.8257 | K8: =I8-J8 -> 4923.9976 | L8: =(Input!$C$21*'Master Table'!G8)+Input!$C$20 -> 6341.28 | M8: =I8-L8 -> 378.54332 | N8: =VLOOKUP(A8,'Good Samaritan Hospital'!$G:$I,3,FALSE) -> 52 | O8: =M8*N8 -> 19684.253 | P8: =F8-0.5 -> 2.4 | Q8: =(P8*Input!$C$21)+Input!$C$20 -> 5620.68 | R8: =-(Q8-L8)*N8 -> 37471.2 | S8: =(Q8-L8)/L8 -> -0.11363636 | T8: =I8-Q8 -> 1099.1433 | U8: =T8*N8 -> 57155.453
A9: 069 | B9: 01 | C9: MED | D9: TRANSIENT ISCHEMIA WITHOUT THROMBOLYTIC | E9: 0.7979 | F9: 2 | G9: =E9*Input!$C$15 -> 4889.2411 | H9: =E9*Input!$C$13 -> 385.9921 | I9: =G9+H9 -> 5275.2332 | J9: =I9*Input!$C$17 -> 1409.7691 | K9: =I9-J9 -> 3865.4641 | L9: =(Input!$C$21*'Master Table'!G9)+Input!$C$20 -> 5044.2 | M9: =I9-L9 -> 231.0332 | N9: =VLOOKUP(A9,'Good Samaritan Hospital'!$G:$I,3,FALSE) -> 11 | O9: =M9*N9 -> 2541.3652 | P9: =F9-0.5 -> 1.5 | Q9: =(P9*Input!$C$21)+Input!$C$20 -> 4323.6 | R9: =-(Q9-L9)*N9 -> 7926.6 | S9: =(Q9-L9)/L9 -> -0.14285714 | T9: =I9-Q9 -> 951.6332 | U9: =T9*N9 -> 10467.965
A10: 070 | B10: 01 | C10: MED | D10: NONSPECIFIC CEREBROVASCULAR DISORDERS WITH MCC | E10: 1.7242 | F10: 4.6 | G10: =E10*Input!$C$15 -> 10565.271 | H10: =E10*Input!$C$13 -> 834.09899 | I10: =G10+H10 -> 11399.37 | J10: =I10*Input!$C$17 -> 3046.4018 | K10: =I10-J10 -> 8352.9679 | L10: =(Input!$C$21*'Master Table'!G10)+Input!$C$20 -> 8791.32 | M10: =I10-L10 -> 2608.0497 | N10: =VLOOKUP(A10,'Good Samaritan Hospital'!$G:$I,3,FALSE) -> 18 | O10: =M10*N10 -> 46944.895 | P10: =F10-0.5 -> 4.1 | Q10: =(P10*Input!$C$21)+Input!$C$20 -> 8070.72 | R10: =-(Q10-L10)*N10 -> 12970.8 | S10: =(Q10-L10)/L10 -> -0.081967213 | T10: =I10-Q10 -> 3328.6497 | U10: =T10*N10 -> 59915.695
A11: 071 | B11: 01 | C11: MED | D11: NONSPECIFIC CEREBROVASCULAR DISORDERS WITH CC | E11: 1.069 | F11: 3.4 | G11: =E11*Input!$C$15 -> 6550.4433 | H11: =E11*Input!$C$13 -> 517.13944 | I11: =G11+H11 -> 7067.5828 | J11: =I11*Input!$C$17 -> 1888.762 | K11: =I11-J11 -> 5178.8207 | L11: =(Input!$C$21*'Master Table'!G11)+Input!$C$20 -> 7061.88 | M11: =I11-L11 -> 5.7027714 | N11: =VLOOKUP(A11,'Good Samaritan Hospital'!$G:$I,3,FALSE) -> 20 | O11: =M11*N11 -> 114.05543 | P11: =F11-0.5 -> 2.9 | Q11: =(P11*Input!$C$21)+Input!$C$20 -> 6341.28 | R11: =-(Q11-L11)*N11 -> 14412 | S11: =(Q11-L11)/L11 -> -0.10204082 | T11: =I11-Q11 -> 726.30277 | U11: =T11*N11 -> 14526.055
A12: 100 | B12: 01 | C12: MED | D12: SEIZURES WITH MCC | E12: 1.921 | F12: 4.4 | G12: =E12*Input!$C$15 -> 11771.19 | H12: =E12*Input!$C$13 -> 929.30296 | I12: =G12+H12 -> 12700.493 | J12: =I12*Input!$C$17 -> 3394.1177 | K12: =I12-J12 -> 9306.3748 | L12: =(Input!$C$21*'Master Table'!G12)+Input!$C$20 -> 8503.08 | M12: =I12-L12 -> 4197.4125 | N12: =VLOOKUP(A12,'Good Samaritan Hospital'!$G:$I,3,FALSE) -> 19 | O12: =M12*N12 -> 79750.838 | P12: =F12-0.5 -> 3.9 | Q12: =(P12*Input!$C$21)+Input!$C$20 -> 7782.48 | R12: =-(Q12-L12)*N12 -> 13691.4 | S12: =(Q12-L12)/L12 -> -0.084745763 | T12: =I12-Q12 -> 4918.0125 | U12: =T12*N12 -> 93442.238
A13: 101 | B13: 01 | C13: MED | D13: SEIZURES WITHOUT MCC | E13: 0.9015 | F13: 2.6 | G13: =E13*Input!$C$15 -> 5524.0642 | H13: =E13*Input!$C$13 -> 436.10964 | I13: =G13+H13 -> 5960.1739 | J13: =I13*Input!$C$17 -> 1592.8147 | K13: =I13-J13 -> 4367.3591 | L13: =(Input!$C$21*'Master Table'!G13)+Input!$C$20 -> 5908.92 | M13: =I13-L13 -> 51.253871 | N13: =VLOOKUP(A13,'Good Samaritan Hospital'!$G:$I,3,FALSE) -> 14 | O13: =M13*N13 -> 717.5542 | P13: =F13-0.5 -> 2.1 | Q13: =(P13*Input!$C$21)+Input!$C$20 -> 5188.32 | R13: =-(Q13-L13)*N13 -> 10088.4 | S13: =(Q13-L13)/L13 -> -0.12195122 | T13: =I13-Q13 -> 771.85387 | U13: =T13*N13 -> 10805.954
A14: 175 | B14: 04 | C14: MED | D14: PULMONARY EMBOLISM WITH MCC OR ACUTE COR PULMONALE | E14: 1.3968 | F14: 3.9 | G14: =E14*Input!$C$15 -> 8559.0825 | H14: =E14*Input!$C$13 -> 675.71597 | I14: =G14+H14 -> 9234.7985 | J14: =I14*Input!$C$17 -> 2467.9353 | K14: =I14-J14 -> 6766.8633 | L14: =(Input!$C$21*'Master Table'!G14)+Input!$C$20 -> 7782.48 | M14: =I14-L14 -> 1452.3185 | N14: =VLOOKUP(A14,'Good Samaritan Hospital'!$G:$I,3,FALSE) -> 16 | O14: =M14*N14 -> 23237.096 | P14: =F14-0.5 -> 3.4 | Q14: =(P14*Input!$C$21)+Input!$C$20 -> 7061.88 | R14: =-(Q14-L14)*N14 -> 11529.6 | S14: =(Q14-L14)/L14 -> -0.092592593 | T14: =I14-Q14 -> 2172.9185 | U14: =T14*N14 -> 34766.696
... A67: 981 | B67: 00 | C67: SURG | D67: EXTENSIVE O.R. PROCEDURES UNRELATED TO PRINCIPAL DIAGNOSIS WITH MCC | E67: 4.5804 | F67: 8.5 | G67: =E67*Input!$C$15 -> 28067.026 | H67: =E67*Input!$C$13 -> 2215.8143 | I67: =G67+H67 -> 30282.84 | J67: =I67*Input!$C$17 -> 8092.8771 | K67: =I67-J67 -> 22189.963 | L67: =(Input!$C$21*'Master Table'!G67)+Input!$C$20 -> 14412 | M67: =I67-L67 -> 15870.84 | N67: =VLOOKUP(A67,'Good Samaritan Hospital'!$G:$I,3,FALSE) -> 11 | O67: =M67*N67 -> 174579.24 | P67: =F67-0.5 -> 8 | Q67: =(P67*Input!$C$21)+Input!$C$20 -> 13691.4 | R67: =-(Q67-L67)*N67 -> 7926.6 | S67: =(Q67-L67)/L67 -> -0.05 | T67: =I67-Q67 -> 16591.44 | U67: =T67*N67 -> 182505.84
L68: =SUM(L3:L67) -> 495772.8 | O68: =SUM(O3:O67) -> 9494691.4 | Q68: =SUM(Q3:Q67) -> 448933.8 | R68: =SUM(R3:R67) -> 1318698 | U68: =SUM(U3:U67) -> 10813389

Sheet Ohio Urban Hospitals Financial 
A1: Provider CCN | B1: Hospital Name | C1: City | D1: State Code | E1: Cost of Uncompensated Care | F1: Total Unreimbursed and Uncompensated Care | G1: Inpatient Total Charges | H1: Outpatient Total Charges | I1: Combined Outpatient + Inpatient Total Charges | J1: Net Income | K1: Cost To Charge Ratio | L1: Net Revenue from Medicaid | M1: Medicaid Charges | N1: CNN | O1: Wage Index 2023 | P1: WI Adjustment Factor
A2: 360189 | B2: MADISON HEALTH | C2: LONDON | D2: OH | E2: 1741928 | F2: 5319204 | G2: 29585933 | H2: 172046507 | I2: 201632440 | J2: 7189024 | K2: 0.228281 | L2: 4628233 | M2: 35944776 | N2: 360189 | O2: 0.9346 | P2: 0.955528
A3: 360351 | B3: CRYSTAL CLINIC ORTHOPAEDIC CENTER | C3: AKRON | D3: OH | E3: 1025756 | F3: 4491088 | G3: 172313981 | H3: 678936357 | I3: 851250338 | J3: 7631624 | K3: 0.20652 | L3: 6048085 | M3: 46065353 | N3: 360351 | O3: 0.836 | P3: 0.88848
A4: 360092 | B4: MEMORIAL HOSPITAL OF UNION COUNTY | C4: MARYSVILLE | D4: OH | E4: 4471898 | F4: 10932284 | G4: 77556405 | H4: 352261915 | I4: 429818320 | J4: 9290339 | K4: 0.31105 | L4: 7711324 | M4: 51379453 | N4: 360092 | O4: 0.9346 | P4: 0.955528
A5: 360263 | B5: INSTITUTE FOR ORTHOPAEDIC SURGERY | C5: LIMA | D5: OH | E5: 419156 | F5: 683481 | G5: 122874994 | H5: 107415737 | I5: 230290731 | J5: 24498430 | K5: 0.158478 | L5: 2504429 | M5: 13684586 | N5: 360263 | O5: 0.8371 | P5: 0.889228
A6: 360091 | B6: MEDINA HOSPITAL | C6: MEDINA | D6: OH | E6: 4447134 | F6: 10292294 | G6: 270076329 | H6: 398838393 | I6: 668914722 | J6: 37423431 | K6: 0.218258 | L6: 9212941 | M6: 63874628 | N6: 360091 | O6: 0.8786 | P6: 0.917448
A7: 360355 | B7: OHIO VALLEY MEDICAL CENTER | C7: SPRINGFIELD | D7: OH | E7: 365939 | F7: 2666009 | G7: 15143058 | H7: 204368197 | I7: 219511255 | J7: 296029 | K7: 0.217378 | L7: 2244566 | M7: 20906605 | N7: 360355 | O7: 0.9642 | P7: 0.975656
A8: 360236 | B8: CLERMONT MERCY HOSPITAL | C8: BATAVIA | D8: OH | E8: 5246054 | F8: 12332775 | G8: 314734848 | H8: 486104315 | I8: 800839163 | J8: 9219955 | K8: 0.170064 | L8: 20253818 | M8: 180472172 | N8: 360236 | O8: 0.9077 | P8: 0.937236
A9: 360259 | B9: BAY PARK COMMUNITY HOSPITAL | C9: OREGON | D9: OH | E9: 1862804 | F9: 3690685 | G9: 148162820 | H9: 409084655 | I9: 557247475 | J9: 23756921 | K9: 0.152879 | L9: 13850359 | M9: 116143871 | N9: 360259 | O9: 0.8511 | P9: 0.898748
A10: 360364 | B10: CLEVELAND CLINIC AVON HOSPITAL | C10: AVON | D10: OH | E10: 5021391 | F10: 11110052 | G10: 243729391 | H10: 517275003 | I10: 761004394 | J10: 47236889 | K10: 0.195926 | L10: 10483663 | M10: 82758381 | N10: 360364 | O10: 0.8786 | P10: 0.917448
A11: 360056 | B11: MERCY HEALTH - FAIRFIELD HOSPITAL | C11: FAIRFIELD | D11: OH | E11: 8425430 | F11: 25179866 | G11: 785732388 | H11: 733039860 | I11: 1518772248 | J11: 3373621 | K11: 0.173561 | L11: 24136341 | M11: 246378622 | N11: 360056 | O11: 0.9077 | P11: 0.937236
A12: 360076 | B12: ATRIUM MEDICAL CENTER | C12: FRANKLIN | D12: OH | E12: 5468933 | F12: 17580285 | G12: 562913619 | H12: 555868521 | I12: 1118782140 | J12: 38192093 | K12: 0.201062 | L12: 27927930 | M12: 211740785 | N12: 360076 | O12: 0.9077 | P12: 0.937236
A13: 360161 | B13: ST. JOSEPH HEALTH CENTER | C13: WARREN | D13: OH | E13: 3558126 | F13: 4805494 | G13: 410002362 | H13: 749669813 | I13: 1159672175 | J13: 27465135 | K13: 0.138405 | L13: 31756356 | M13: 274448914 | N13: 360161 | O13: 0.8307 | P13: 0.884876
... A35: 360001 | B35: MERCY HOSPITAL ANDERSON | C35: CINCINNATI | D35: OH | E35: 7670126 | F35: 20810459 | G35: 766247143 | H35: 495107725 | I35: 1261354868 | J35: 8751112 | K35: 0.181213 | L35: 18187258 | M35: 177111959 | N35: 360001 | O35: 0.9077 | P35: 0.937236
A36: 360247 | B36: PARKSIDE BEHAVIORAL HEALTHCARE ACQUI | C36: GAHANNA | D36: OH | E36: 9915 | F36: 9915 | G36: 1994520 | I36: 1994520 | J36: -993937 | K36: 1.075599 | N36: 360247 | O36: 0.9346 | P36: 0.955528
A37: 360006 | B37: RIVERSIDE METHODIST HOSPITAL | C37: COLUMBUS | D37: OH | E37: 68376288 | F37: 138007383 | G37: 3484325500 | H37: 2364723162 | I37: 5849048662 | J37: 102500729 | K37: 0.213153 | L37: 85667934 | M37: 783087391 | N37: 360006 | O37: 0.9346 | P37: 0.955528
A38: 360012 | B38: ST. ANNS HOSPITAL | C38: WESTERVILLE | D38: OH | E38: 35361387 | F38: 40201225 | G38: 809942150 | H38: 707211005 | I38: 1517153155 | J38: 40592518 | K38: 0.227039 | L38: 45103852 | M38: 219978463 | N38: 360012 | O38: 0.9346 | P38: 0.955528
A39: 360029 | B39: WOOD COUNTY HOSPITAL | C39: BOWLING GREEN | D39: OH | E39: 3366746 | F39: 6810944 | G39: 50302051 | H39: 211575528 | I39: 261877579 | J39: 13399986 | K39: 0.355732 | L39: 8129263 | M39: 32017053 | N39: 360029 | O39: 0.8511 | P39: 0.898748
A40: 360035 | B40: MOUNT CARMEL HEALTH | C40: COLUMBUS | D40: OH | E40: 66431678 | F40: 77643714 | G40: 1938357086 | H40: 1326393071 | I40: 3264750157 | J40: -28137140 | K40: 0.210133 | L40: 87358291 | M40: 469085423 | N40: 360035 | O40: 0.9346 | P40: 0.955528
A41: 360163 | B41: THE CHRIST HOSPITAL | C41: CINCINNATI | D41: OH | E41: 13543963 | F41: 47445511 | G41: 1503284814 | H41: 1889945307 | I41: 3393230121 | J41: 177848184 | K41: 0.258622 | L41: 49983204 | M41: 324352731 | N41: 360163 | O41: 0.9077 | P41: 0.937236
A42: 360170 | B42: BERGER HOSPITAL | C42: CIRCLEVILLE | D42: OH | E42: 4632315 | F42: 12010208 | G42: 84292511 | H42: 302308407 | I42: 386600918 | J42: 22600800 | K42: 0.264876 | L42: 9365405 | M42: 70239813 | N42: 360170 | O42: 0.9346 | P42: 0.955528
A43: 360210 | B43: GRADY MEMORIAL HOSPITAL | C43: DELAWARE | D43: OH | E43: 5579377 | F43: 11759313 | G43: 83084005 | H43: 346616112 | I43: 429700117 | J43: 22934010 | K43: 0.253773 | L43: 6349127 | M43: 51397975 | N43: 360210 | O43: 0.9346 | P43: 0.955528
A44: 360266 | B44: MOUNT CARMEL NEW ALBANY HOSPITAL | C44: NEW ALBANY | D44: OH | E44: 845924 | F44: 4612329 | G44: 121137574 | H44: 225141657 | I44: 346279231 | J44: 15251446 | K44: 0.20155 | L44: -1347278 | M44: 12002613 | N44: 360266 | O44: 0.9346 | P44: 0.955528
A45: 360358 | B45: DILEY RIDGE MEDICAL CENTER | C45: CANAL WINCHESTER | D45: OH | E45: 3548288 | F45: 3580982 | G45: 3836886 | H45: 99804842 | I45: 103641728 | J45: 11827432 | K45: 0.142919 | L45: 2729331 | M45: 19325807 | N45: 360358 | O45: 0.9346 | P45: 0.955528
A46: 360017 | B46: GRANT MEDICAL CENTER | C46: COLUMBUS | D46: OH | E46: 65380242 | F46: 111733990 | G46: 1803654552 | H46: 2761610716 | I46: 4565265268 | J46: 165522114 | K46: 0.195227 | L46: 127304776 | M46: 1046945762 | N46: 360017 | O46: 0.9346 | P46: 0.955528
A47: 360134 | B47: GOOD SAMARITAN HOSPITAL | C47: CINCINNATI | D47: OH | E47: 20525726 | F47: 28080689 | G47: 947583464 | H47: 1852073040 | I47: 2799656504 | J47: -5240692 | K47: 0.267243 | L47: 94196671 | M47: 478807140 | N47: 360134 | O47: 0.9077 | P47: 0.937236
A48: 360152 | B48: DOCTORS HOSPITAL | C48: COLUMBUS | D48: OH | E48: 29329120 | F48: 37143144 | G48: 558718818 | H48: 671968880 | I48: 1230687698 | J48: -1262924 | K48: 0.194911 | L48: 40982002 | M48: 330812000 | N48: 360152 | O48: 0.9346 | P48: 0.955528
... A53: 360354 | B53: WEST CHESTER HOSPITAL LLC | C53: WEST CHESTER | D53: OH | E53: 9167472 | F53: 17970607 | G53: 528494226 | H53: 764066766 | I53: 1292560992 | J53: 886131 | K53: 0.197716 | L53: 24264270 | M53: 175122655 | N53: 360354 | O53: 0.9077 | P53: 0.937236
K57: =AVERAGE(K2:K53) -> 0.23538052

Sheet Good Samaritan Hospital
B2: Rndrng_Prvdr_CCN | C2: Rndrng_Prvdr_Org_Name | D2: Rndrng_Prvdr_City | E2: Rndrng_Prvdr_State_Abrvtn | F2: DRG_Cd | G2: DRG_Cd_c | H2: DRG_Desc | I2: Tot_Dschrgs | J2: Avg_Submtd_Cvrd_Chrg | K2: Avg_Tot_Pymt_Amt | L2: Avg_Mdcr_Pymt_Amt
B3: 360134 | C3: Good Samaritan Hospital | D3: Cincinnati | E3: OH | F3: 023 | G3: =TRIM(F3) -> 023 | H3: CRANIOTOMY WITH MAJOR DEVICE IMPLANT OR ACUTE COMPLEX CNS PRINCIPAL DIAGNOSIS WITH MCC O | I3: 14 | J3: 141446.64 | K3: 60670.214 | L3: 31204
B4: 360134 | C4: Good Samaritan Hospital | D4: Cincinnati | E4: OH | F4: 025 | G4: =TRIM(F4) -> 025 | H4: CRANIOTOMY AND ENDOVASCULAR INTRACRANIAL PROCEDURES WITH MCC | I4: 23 | J4: 101374.43 | K4: 41018.522 | L4: 26919.522
B5: 360134 | C5: Good Samaritan Hospital | D5: Cincinnati | E5: OH | F5: 027 | G5: =TRIM(F5) -> 027 | H5: CRANIOTOMY AND ENDOVASCULAR INTRACRANIAL PROCEDURES WITHOUT CC/MCC | I5: 15 | J5: 91108.4 | K5: 23813.733 | L5: 13990.267
B6: 360134 | C6: Good Samaritan Hospital | D6: Cincinnati | E6: OH | F6: 057 | G6: =TRIM(F6) -> 057 | H6: DEGENERATIVE NERVOUS SYSTEM DISORDERS WITHOUT MCC | I6: 14 | J6: 25478.643 | K6: 12673.071 | L6: 8852.0714
B7: 360134 | C7: Good Samaritan Hospital | D7: Cincinnati | E7: OH | F7: 064 | G7: =TRIM(F7) -> 064 | H7: INTRACRANIAL HEMORRHAGE OR CEREBRAL INFARCTION WITH MCC | I7: 67 | J7: 59645.328 | K7: 19133 | L7: 13206.567
B8: 360134 | C8: Good Samaritan Hospital | D8: Cincinnati | E8: OH | F8: 065 | G8: =TRIM(F8) -> 065 | H8: INTRACRANIAL HEMORRHAGE OR CEREBRAL INFARCTION WITH CC OR TPA IN 24 HOURS | I8: 52 | J8: 33174.981 | K8: 9787.0962 | L8: 6578.0962
B9: 360134 | C9: Good Samaritan Hospital | D9: Cincinnati | E9: OH | F9: 069 | G9: =TRIM(F9) -> 069 | H9: TRANSIENT ISCHEMIA WITHOUT THROMBOLYTIC | I9: 11 | J9: 19884.545 | K9: 7491 | L9: 5214.3636
B10: 360134 | C10: Good Samaritan Hospital | D10: Cincinnati | E10: OH | F10: 070 | G10: =TRIM(F10) -> 070 | H10: NONSPECIFIC CEREBROVASCULAR DISORDERS WITH MCC | I10: 18 | J10: 46881.444 | K10: 16523.889 | L10: 10793.222
B11: 360134 | C11: Good Samaritan Hospital | D11: Cincinnati | E11: OH | F11: 071 | G11: =TRIM(F11) -> 071 | H11: NONSPECIFIC CEREBROVASCULAR DISORDERS WITH CC | I11: 20 | J11: 25571.3 | K11: 10019.3 | L11: 7711.45
B12: 360134 | C12: Good Samaritan Hospital | D12: Cincinnati | E12: OH | F12: 100 | G12: =TRIM(F12) -> 100 | H12: SEIZURES WITH MCC | I12: 19 | J12: 66672.368 | K12: 15859.211 | L12: 11291.526
B13: 360134 | C13: Good Samaritan Hospital | D13: Cincinnati | E13: OH | F13: 101 | G13: =TRIM(F13) -> 101 | H13: SEIZURES WITHOUT MCC | I13: 14 | J13: 34589.071 | K13: 9322.7143 | L13: 6042.2143
B14: 360134 | C14: Good Samaritan Hospital | D14: Cincinnati | E14: OH | F14: 175 | G14: =TRIM(F14) -> 175 | H14: PULMONARY EMBOLISM WITH MCC OR ACUTE COR PULMONALE | I14: 16 | J14: 41438.125 | K14: 13423 | L14: 9179.6875
B15: 360134 | C15: Good Samaritan Hospital | D15: Cincinnati | E15: OH | F15: 177 | G15: =TRIM(F15) -> 177 | H15: RESPIRATORY INFECTIONS AND INFLAMMATIONS WITH MCC | I15: 57 | J15: 35904.596 | K15: 16065.754 | L15: 12774.263
B16: 360134 | C16: Good Samaritan Hospital | D16: Cincinnati | E16: OH | F16: 178 | G16: =TRIM(F16) -> 178 | H16: RESPIRATORY INFECTIONS AND INFLAMMATIONS WITH CC | I16: 11 | J16: 23015 | K16: 10523.636 | L16: 7913.3636
B17: 360134 | C17: Good Samaritan Hospital | D17: Cincinnati | E17: OH | F17: 189 | G17: =TRIM(F17) -> 189 | H17: PULMONARY EDEMA AND RESPIRATORY FAILURE | I17: 60 | J17: 34908.65 | K17: 11457.4 | L17: 8740.8833
B18: 360134 | C18: Good Samaritan Hospital | D18: Cincinnati | E18: OH | F18: 193 | G18: =TRIM(F18) -> 193 | H18: SIMPLE PNEUMONIA AND PLEURISY WITH MCC | I18: 39 | J18: 36581.897 | K18: 12335.513 | L18: 8602.7949
B19: 360134 | C19: Good Samaritan Hospital | D19: Cincinnati | E19: OH | F19: 208 | G19: =TRIM(F19) -> 208 | H19: RESPIRATORY SYSTEM DIAGNOSIS WITH VENTILATOR SUPPORT <=96 HOURS | I19: 17 | J19: 76699.353 | K19: 22614.588 | L19: 16981.412
B20: 360134 | C20: Good Samaritan Hospital | D20: Cincinnati | E20: OH | F20: 246 | G20: =TRIM(F20) -> 246 | H20: PERCUTANEOUS CARDIOVASCULAR PROCEDURES WITH DRUG-ELUTING STENT WITH MCC OR 4+ ARTERIES O | I20: 15 | J20: 88044.2 | K20: 26070.067 | L20: 20444.867
B21: 360134 | C21: Good Samaritan Hospital | D21: Cincinnati | E21: OH | F21: 247 | G21: =TRIM(F21) -> 247 | H21: PERCUTANEOUS CARDIOVASCULAR PROCEDURES WITH DRUG-ELUTING STENT WITHOUT MCC | I21: 15 | J21: 76441.2 | K21: 18071.933 | L21: 11576.2
B22: 360134 | C22: Good Samaritan Hospital | D22: Cincinnati | E22: OH | F22: 269 | G22: =TRIM(F22) -> 269 | H22: AORTIC AND HEART ASSIST PROCEDURES EXCEPT PULSATION BALLOON WITHOUT MCC | I22: 12 | J22: 117925 | K22: 32932.833 | L22: 30939.917
B23: 360134 | C23: Good Samaritan Hospital | D23: Cincinnati | E23: OH | F23: 280 | G23: =TRIM(F23) -> 280 | H23: ACUTE MYOCARDIAL INFARCTION, DISCHARGED ALIVE WITH MCC | I23: 46 | J23: 41971.522 | K23: 14275.652 | L23: 10185.761
... B66: 360134 | C66: Good Samaritan Hospital | D66: Cincinnati | E66: OH | F66: 948 | G66: =TRIM(F66) -> 948 | H66: SIGNS AND SYMPTOMS WITHOUT MCC | I66: 18 | J66: 20756.278 | K66: 8105.8889 | L66: 5469.2222
B67: 360134 | C67: Good Samaritan Hospital | D67: Cincinnati | E67: OH | F67: 981 | G67: =TRIM(F67) -> 981 | H67: EXTENSIVE O.R. PROCEDURES UNRELATED TO PRINCIPAL DIAGNOSIS WITH MCC | I67: 11 | J67: 93427 | K67: 45048.182
